{"assets/icons/.DS_Store":["assets/icons/.DS_Store"],"assets/icons/analyze.png":["assets/icons/analyze.png"],"assets/icons/category.png":["assets/icons/category.png"],"assets/icons/icon.jpeg":["assets/icons/icon.jpeg"],"assets/icons/menu.png":["assets/icons/menu.png"],"assets/images/.DS_Store":["assets/images/.DS_Store"],"assets/images/background.png":["assets/images/background.png"],"assets/images/eth_logo.png":["assets/images/eth_logo.png"],"assets/images/nft/artists/fewocious.jpeg":["assets/images/nft/artists/fewocious.jpeg"],"assets/images/nft/artists/fraile.jpeg":["assets/images/nft/artists/fraile.jpeg"],"assets/images/nft/artists/hobbs.jpeg":["assets/images/nft/artists/hobbs.jpeg"],"assets/images/nft/artists/johnson.jpeg":["assets/images/nft/artists/johnson.jpeg"],"assets/images/nft/artists/jones.jpeg":["assets/images/nft/artists/jones.jpeg"],"assets/images/nft/artists/kim.jpeg":["assets/images/nft/artists/kim.jpeg"],"assets/images/nft/artists/mad_dog.png":["assets/images/nft/artists/mad_dog.png"],"assets/images/nft/artists/winklemann.jpeg":["assets/images/nft/artists/winklemann.jpeg"],"assets/images/nft/nfts/.DS_Store":["assets/images/nft/nfts/.DS_Store"],"assets/images/nft/nfts/3d.jpeg":["assets/images/nft/nfts/3d.jpeg"],"assets/images/nft/nfts/abstract.png":["assets/images/nft/nfts/abstract.png"],"assets/images/nft/nfts/angel.jpeg":["assets/images/nft/nfts/angel.jpeg"],"assets/images/nft/nfts/art.png":["assets/images/nft/nfts/art.png"],"assets/images/nft/nfts/astronat2.jpeg":["assets/images/nft/nfts/astronat2.jpeg"],"assets/images/nft/nfts/astronaut.jpeg":["assets/images/nft/nfts/astronaut.jpeg"],"assets/images/nft/nfts/cat.jpeg":["assets/images/nft/nfts/cat.jpeg"],"assets/images/nft/nfts/dessert.jpeg":["assets/images/nft/nfts/dessert.jpeg"],"assets/images/nft/nfts/digital_art.jpeg":["assets/images/nft/nfts/digital_art.jpeg"],"assets/images/nft/nfts/glass.jpeg":["assets/images/nft/nfts/glass.jpeg"],"assets/images/nft/nfts/monkey.jpeg":["assets/images/nft/nfts/monkey.jpeg"],"assets/images/nft/nfts/monkey2.jpeg":["assets/images/nft/nfts/monkey2.jpeg"],"assets/images/nft/nfts/nature.jpeg":["assets/images/nft/nfts/nature.jpeg"],"assets/images/nft/nfts/owl.jpeg":["assets/images/nft/nfts/owl.jpeg"],"assets/images/nft/nfts/pink_tree.jpeg":["assets/images/nft/nfts/pink_tree.jpeg"],"assets/images/nft/nfts/portrait.jpeg":["assets/images/nft/nfts/portrait.jpeg"],"assets/images/nft/nfts/sci_fi.jpeg":["assets/images/nft/nfts/sci_fi.jpeg"],"assets/images/nft/nfts/space.jpeg":["assets/images/nft/nfts/space.jpeg"],"assets/images/nft/nfts/woman.jpeg":["assets/images/nft/nfts/woman.jpeg"],"assets/images/polygon.png":["assets/images/polygon.png"],"packages/cupertino_icons/assets/CupertinoIcons.ttf":["packages/cupertino_icons/assets/CupertinoIcons.ttf"]}